<?xml version="1.0" encoding="UTF-8"?>
<databaseChangeLog
    xmlns="http://www.liquibase.org/xml/ns/dbchangelog"
    xmlns:xsi="http://www.w3.org/2001/XMLSchema-instance"
    xsi:schemaLocation="http://www.liquibase.org/xml/ns/dbchangelog
        http://www.liquibase.org/xml/ns/dbchangelog/dbchangelog-latest.xsd">

    <changeSet id="20260403-04-create-projects" author="myrmec">
        <preConditions onFail="MARK_RAN">
            <not>
                <tableExists tableName="projects"/>
            </not>
        </preConditions>
        <comment>Create projects table - container for workflows</comment>

        <createTable tableName="projects">
            <column name="id" type="uuid">
                <constraints primaryKey="true" nullable="false"/>
            </column>
            <column name="name" type="varchar(200)">
                <constraints nullable="false" unique="true" uniqueConstraintName="uk_projects_name"/>
            </column>
            <column name="description" type="text"/>
            <column name="status" type="varchar(20)" defaultValue="ACTIVE">
                <constraints nullable="false"/>
            </column>
            <column name="workspace_repo_url" type="varchar(500)"/>
            <column name="workspace_repo_branch" type="varchar(100)" defaultValue="main"/>
            <column name="workspace_credential_secret_id" type="uuid"/>
            <column name="rag_config" type="text"/>
            <column name="created_at" type="timestamp with time zone" defaultValueComputed="CURRENT_TIMESTAMP">
                <constraints nullable="false"/>
            </column>
            <column name="updated_at" type="timestamp with time zone"/>
        </createTable>

        <createIndex indexName="idx_projects_status" tableName="projects">
            <column name="status"/>
        </createIndex>
    </changeSet>

</databaseChangeLog>
